ply/__init__.py
ply/bitnet.py
ply/flash_attn.py
ply/fp4_experimental.py
ply/linear.py
ply/moe.py
ply/paged_attn.py
ply/rmsnorm.py
ply/rope.py
ply/vision/__init__.py
ply/vision/pool.py
ply/vision/vit.py
ply_ai-1.0.5.dist-info/METADATA
ply_ai-1.0.5.dist-info/WHEEL
ply_ai-1.0.5.dist-info/top_level.txt
ply_ai-1.0.5.dist-info/RECORD
