Metadata-Version: 2.4
Name: ply-AI
Version: 1.0.5
Summary: Hardware-aware Triton accelerator library
Author: Zeng Jianrong
Author-email: zeng@ply-ai.com
Classifier: Programming Language :: Python :: 3
Requires-Dist: torch
Requires-Dist: triton
Dynamic: author
Dynamic: author-email
Dynamic: classifier
Dynamic: description
Dynamic: description-content-type
Dynamic: requires-dist
Dynamic: summary
